MANIFEST.in
README.txt
setup.py
async_reports/__init__.py
async_reports/celeryconfig.py
async_reports/formatter.py
async_reports/manage.py
async_reports/report.py
async_reports/report_handler.py
async_reports/settings.py
async_reports/test_settings.py
async_reports/tests.py
async_reports/urls.py
async_reports/report_tracking/__init__.py
async_reports/report_tracking/admin.py
async_reports/report_tracking/models.py
async_reports/report_tracking/report_handler.py
async_reports/report_tracking/views.py
async_reports/report_tracking/migrations/0001_initial.py
async_reports/report_tracking/migrations/0002_auto__add_field_reporttracking_data.py
async_reports/report_tracking/migrations/__init__.py
async_reports/report_tracking/templatetags/__init__.py
async_reports/report_tracking/templatetags/report_lists.py
async_reports/templates/report_tracking/reports.html
django_async_reports.egg-info/PKG-INFO
django_async_reports.egg-info/SOURCES.txt
django_async_reports.egg-info/dependency_links.txt
django_async_reports.egg-info/requires.txt
django_async_reports.egg-info/top_level.txt