Metadata-Version: 1.0
Name: django-async-reports
Version: 0.2.00
Summary: Reporting for django
Home-page: UNKNOWN
Author: Anthony TRESONTANI
Author-email: dev.tresontani@gmail.com
License: UNKNOWN
Keywords: CSV Django reporting
Platform: UNKNOWN
Classifier: Environment :: Web Environment
Classifier: Development Status :: 2 - Pre-Alpha
Classifier: Framework :: Django
Classifier: Intended Audience :: Developers
Classifier: License :: OSI Approved :: BSD License
Classifier: Operating System :: Unix
Classifier: Programming Language :: Python
